mycalc/calculator.py
kyeongmo230411-0.0.1.dist-info/METADATA
kyeongmo230411-0.0.1.dist-info/WHEEL
kyeongmo230411-0.0.1.dist-info/top_level.txt
kyeongmo230411-0.0.1.dist-info/RECORD
