Metadata-Version: 2.1
Name: kyeongmo230411
Version: 0.0.1
Summary: nice calculator
Home-page: https://github.com/kimkyeongmo/abc
Download-URL: https://github.com/kimkyeongmo/abc/defg.zip
Author: 
License: UNKNOWN
Platform: UNKNOWN
Classifier: Programming Language :: Python :: 3
